[{"session_key": 9566, "meeting_key": 1241, "driver_number": 1, "date": "2024-07-21T12:08:02.951000+00:00", "position": 3}, {"session_key": 9566, "meeting_key": 1241, "driver_number": 2, "date": "2024-07-21T12:08:02.951000+00:00", "position": 14}, {"session_key": 9566, "meeting_key": 1241, "driver_number": 3, "date": "2024-07-21T12:08:02.951000+00:00", "position": 9}, {"session_key": 9566, "meeting_key": 1241, "driver_number": 4, "date": "2024-07-21T12:08:02.951000+00:00", "position": 1}, {"session_key": 9566, "meeting_key": 1241, "driver_number": 10, "date": "2024-07-21T12:08:02.951000+00:00", "position": 20}, {"session_key": 9566, "meeting_key": 1241, "driver_number": 11, "date": "2024-07-21T12:08:02.951000+00:00", "position": 16}, {"session_key": 9566, "meeting_key": 1241, "driver_number": 14, "date": "2024-07-21T12:08:02.951000+00:00", "position": 7}, {"session_key": 9566, "meeting_key": 1241, "driver_number": 16, "date": "2024-07-21T12:08:02.951000+00:00", "position": 6}, {"session_key": 9566, "meeting_key": 1241, "driver_number": 18, "date": "2024-07-21T12:08:02.951000+00:00", "position": 8}, {"session_key": 9566, "meeting_key": 1241, "driver_number": 20, "date": "2024-07-21T12:08:02.951000+00:00", "position": 15}, {"session_key": 9566, "meeting_key": 1241, "driver_number": 22, "date": "2024-07-21T12:08:02.951000+00:00", "position": 10}, {"session_key": 9566, "meeting_key": 1241, "driver_number": 23, "date": "2024-07-21T12:08:02.951000+00:00", "position": 13}, {"session_key": 9566, "meeting_key": 1241, "driver_number": 24, "date": "2024-07-21T12:08:02.951000+00:00", "position": 18}, {"session_key": 9566, "meeting_key": 1241, "driver_number": 27, "date": "2024-07-21T12:08:02.951000+00:00", "position": 11}, {"session_key": 9566, "meeting_key": 1241, "driver_number": 31, "date": "2024-07-21T12:08:02.951000+00:00", "position": 19}, {"session_key": 9566, "meeting_key": 1241, "driver_number": 44, "date": "2024-07-21T12:08:02.951000+00:00", "position": 5}, {"session_key": 9566, "meeting_key": 1241, "driver_number": 55, "date": "2024-07-21T12:08:02.951000+00:00", "position": 4}, {"session_key": 9566, "meeting_key": 1241, "driver_number": 63, "date": "2024-07-21T12:08:02.951000+00:00", "position": 17}, {"session_key": 9566, "meeting_key": 1241, "driver_number": 77, "date": "2024-07-21T12:08:02.951000+00:00", "position": 12}, {"session_key": 9566, "meeting_key": 1241, "driver_number": 81, "date": "2024-07-21T12:08:02.951000+00:00", "position": 2}, {"session_key": 9566, "meeting_key": 1241, "driver_number": 4, "date": "2024-07-21T13:03:32.416000+00:00", "position": 2}, {"session_key": 9566, "meeting_key": 1241, "driver_number": 81, "date": "2024-07-21T13:03:32.416000+00:00", "position": 1}, {"session_key": 9566, "meeting_key": 1241, "driver_number": 1, "date": "2024-07-21T13:03:33.331000+00:00", "position": 2}, {"session_key": 9566, "meeting_key": 1241, "driver_number": 4, "date": "2024-07-21T13:03:33.331000+00:00", "position": 3}, {"session_key": 9566, "meeting_key": 1241, "driver_number": 44, "date": "2024-07-21T13:03:34.201000+00:00", "position": 4}, {"session_key": 9566, "meeting_key": 1241, "driver_number": 55, "date": "2024-07-21T13:03:34.201000+00:00", "position": 5}, {"session_key": 9566, "meeting_key": 1241, "driver_number": 16, "date": "2024-07-21T13:03:34.261000+00:00", "position": 5}, {"session_key": 9566, "meeting_key": 1241, "driver_number": 55, "date": "2024-07-21T13:03:34.261000+00:00", "position": 6}, {"session_key": 9566, "meeting_key": 1241, "driver_number": 14, "date": "2024-07-21T13:03:34.485000+00:00", "position": 6}, {"session_key": 9566, "meeting_key": 1241, "driver_number": 55, "date": "2024-07-21T13:03:34.485000+00:00", "position": 7}, {"session_key": 9566, "meeting_key": 1241, "driver_number": 3, "date": "2024-07-21T13:03:35.071000+00:00", "position": 10}, {"session_key": 9566, "meeting_key": 1241, "driver_number": 22, "date": "2024-07-21T13:03:35.071000+00:00", "position": 11}, {"session_key": 9566, "meeting_key": 1241, "driver_number": 23, "date": "2024-07-21T13:03:35.071000+00:00", "position": 9}, {"session_key": 9566, "meeting_key": 1241, "driver_number": 27, "date": "2024-07-21T13:03:35.071000+00:00", "position": 12}, {"session_key": 9566, "meeting_key": 1241, "driver_number": 77, "date": "2024-07-21T13:03:35.071000+00:00", "position": 13}, {"session_key": 9566, "meeting_key": 1241, "driver_number": 2, "date": "2024-07-21T13:03:35.473000+00:00", "position": 15}, {"session_key": 9566, "meeting_key": 1241, "driver_number": 20, "date": "2024-07-21T13:03:35.473000+00:00", "position": 11}, {"session_key": 9566, "meeting_key": 1241, "driver_number": 22, "date": "2024-07-21T13:03:35.473000+00:00", "position": 12}, {"session_key": 9566, "meeting_key": 1241, "driver_number": 27, "date": "2024-07-21T13:03:35.473000+00:00", "position": 13}, {"session_key": 9566, "meeting_key": 1241, "driver_number": 77, "date": "2024-07-21T13:03:35.473000+00:00", "position": 14}, {"session_key": 9566, "meeting_key": 1241, "driver_number": 27, "date": "2024-07-21T13:03:35.978000+00:00", "position": 14}, {"session_key": 9566, "meeting_key": 1241, "driver_number": 77, "date": "2024-07-21T13:03:35.978000+00:00", "position": 13}, {"session_key": 9566, "meeting_key": 1241, "driver_number": 2, "date": "2024-07-21T13:03:36.596000+00:00", "position": 16}, {"session_key": 9566, "meeting_key": 1241, "driver_number": 11, "date": "2024-07-21T13:03:36.596000+00:00", "position": 17}, {"session_key": 9566, "meeting_key": 1241, "driver_number": 24, "date": "2024-07-21T13:03:36.596000+00:00", "position": 19}, {"session_key": 9566, "meeting_key": 1241, "driver_number": 31, "date": "2024-07-21T13:03:36.596000+00:00", "position": 15}, {"session_key": 9566, "meeting_key": 1241, "driver_number": 63, "date": "2024-07-21T13:03:36.596000+00:00", "position": 18}, {"session_key": 9566, "meeting_key": 1241, "driver_number": 2, "date": "2024-07-21T13:03:36.704000+00:00", "position": 17}, {"session_key": 9566, "meeting_key": 1241, "driver_number": 11, "date": "2024-07-21T13:03:36.704000+00:00", "position": 18}, {"session_key": 9566, "meeting_key": 1241, "driver_number": 63, "date": "2024-07-21T13:03:36.704000+00:00", "position": 16}, {"session_key": 9566, "meeting_key": 1241, "driver_number": 2, "date": "2024-07-21T13:03:36.882000+00:00", "position": 18}, {"session_key": 9566, "meeting_key": 1241, "driver_number": 11, "date": "2024-07-21T13:03:36.882000+00:00", "position": 17}, {"session_key": 9566, "meeting_key": 1241, "driver_number": 2, "date": "2024-07-21T13:03:37.185000+00:00", "position": 19}, {"session_key": 9566, "meeting_key": 1241, "driver_number": 24, "date": "2024-07-21T13:03:37.185000+00:00", "position": 18}, {"session_key": 9566, "meeting_key": 1241, "driver_number": 3, "date": "2024-07-21T13:04:32.680000+00:00", "position": 11}, {"session_key": 9566, "meeting_key": 1241, "driver_number": 20, "date": "2024-07-21T13:04:32.680000+00:00", "position": 10}, {"session_key": 9566, "meeting_key": 1241, "driver_number": 2, "date": "2024-07-21T13:04:36.489000+00:00", "position": 18}, {"session_key": 9566, "meeting_key": 1241, "driver_number": 24, "date": "2024-07-21T13:04:36.489000+00:00", "position": 19}, {"session_key": 9566, "meeting_key": 1241, "driver_number": 27, "date": "2024-07-21T13:06:02.031000+00:00", "position": 15}, {"session_key": 9566, "meeting_key": 1241, "driver_number": 31, "date": "2024-07-21T13:06:02.031000+00:00", "position": 14}, {"session_key": 9566, "meeting_key": 1241, "driver_number": 27, "date": "2024-07-21T13:06:02.705000+00:00", "position": 16}, {"session_key": 9566, "meeting_key": 1241, "driver_number": 63, "date": "2024-07-21T13:06:02.705000+00:00", "position": 15}, {"session_key": 9566, "meeting_key": 1241, "driver_number": 2, "date": "2024-07-21T13:06:03.355000+00:00", "position": 16}, {"session_key": 9566, "meeting_key": 1241, "driver_number": 11, "date": "2024-07-21T13:06:03.355000+00:00", "position": 18}, {"session_key": 9566, "meeting_key": 1241, "driver_number": 27, "date": "2024-07-21T13:06:03.355000+00:00", "position": 17}, {"session_key": 9566, "meeting_key": 1241, "driver_number": 14, "date": "2024-07-21T13:07:22.261000+00:00", "position": 7}, {"session_key": 9566, "meeting_key": 1241, "driver_number": 55, "date": "2024-07-21T13:07:22.261000+00:00", "position": 6}, {"session_key": 9566, "meeting_key": 1241, "driver_number": 11, "date": "2024-07-21T13:07:29.811000+00:00", "position": 17}, {"session_key": 9566, "meeting_key": 1241, "driver_number": 27, "date": "2024-07-21T13:07:29.811000+00:00", "position": 18}, {"session_key": 9566, "meeting_key": 1241, "driver_number": 24, "date": "2024-07-21T13:07:30.439000+00:00", "position": 18}, {"session_key": 9566, "meeting_key": 1241, "driver_number": 27, "date": "2024-07-21T13:07:30.439000+00:00", "position": 19}, {"session_key": 9566, "meeting_key": 1241, "driver_number": 10, "date": "2024-07-21T13:07:30.881000+00:00", "position": 19}, {"session_key": 9566, "meeting_key": 1241, "driver_number": 27, "date": "2024-07-21T13:07:30.881000+00:00", "position": 20}, {"session_key": 9566, "meeting_key": 1241, "driver_number": 1, "date": "2024-07-21T13:08:40.635000+00:00", "position": 3}, {"session_key": 9566, "meeting_key": 1241, "driver_number": 4, "date": "2024-07-21T13:08:40.635000+00:00", "position": 2}, {"session_key": 9566, "meeting_key": 1241, "driver_number": 3, "date": "2024-07-21T13:11:44.310000+00:00", "position": 9}, {"session_key": 9566, "meeting_key": 1241, "driver_number": 20, "date": "2024-07-21T13:11:44.310000+00:00", "position": 11}, {"session_key": 9566, "meeting_key": 1241, "driver_number": 23, "date": "2024-07-21T13:11:44.310000+00:00", "position": 10}, {"session_key": 9566, "meeting_key": 1241, "driver_number": 20, "date": "2024-07-21T13:11:45.183000+00:00", "position": 12}, {"session_key": 9566, "meeting_key": 1241, "driver_number": 22, "date": "2024-07-21T13:11:45.183000+00:00", "position": 10}, {"session_key": 9566, "meeting_key": 1241, "driver_number": 23, "date": "2024-07-21T13:11:45.183000+00:00", "position": 11}, {"session_key": 9566, "meeting_key": 1241, "driver_number": 20, "date": "2024-07-21T13:11:45.978000+00:00", "position": 13}, {"session_key": 9566, "meeting_key": 1241, "driver_number": 77, "date": "2024-07-21T13:11:45.978000+00:00", "position": 12}, {"session_key": 9566, "meeting_key": 1241, "driver_number": 31, "date": "2024-07-21T13:11:47.296000+00:00", "position": 15}, {"session_key": 9566, "meeting_key": 1241, "driver_number": 63, "date": "2024-07-21T13:11:47.296000+00:00", "position": 14}, {"session_key": 9566, "meeting_key": 1241, "driver_number": 2, "date": "2024-07-21T13:11:48.074000+00:00", "position": 15}, {"session_key": 9566, "meeting_key": 1241, "driver_number": 31, "date": "2024-07-21T13:11:48.074000+00:00", "position": 16}, {"session_key": 9566, "meeting_key": 1241, "driver_number": 11, "date": "2024-07-21T13:11:48.612000+00:00", "position": 16}, {"session_key": 9566, "meeting_key": 1241, "driver_number": 31, "date": "2024-07-21T13:11:48.612000+00:00", "position": 17}, {"session_key": 9566, "meeting_key": 1241, "driver_number": 24, "date": "2024-07-21T13:11:49.277000+00:00", "position": 17}, {"session_key": 9566, "meeting_key": 1241, "driver_number": 31, "date": "2024-07-21T13:11:49.277000+00:00", "position": 18}, {"session_key": 9566, "meeting_key": 1241, "driver_number": 14, "date": "2024-07-21T13:13:07.302000+00:00", "position": 8}, {"session_key": 9566, "meeting_key": 1241, "driver_number": 18, "date": "2024-07-21T13:13:07.302000+00:00", "position": 7}, {"session_key": 9566, "meeting_key": 1241, "driver_number": 3, "date": "2024-07-21T13:13:09.818000+00:00", "position": 10}, {"session_key": 9566, "meeting_key": 1241, "driver_number": 22, "date": "2024-07-21T13:13:09.818000+00:00", "position": 9}, {"session_key": 9566, "meeting_key": 1241, "driver_number": 23, "date": "2024-07-21T13:13:11.109000+00:00", "position": 12}, {"session_key": 9566, "meeting_key": 1241, "driver_number": 77, "date": "2024-07-21T13:13:11.109000+00:00", "position": 11}, {"session_key": 9566, "meeting_key": 1241, "driver_number": 20, "date": "2024-07-21T13:13:11.800000+00:00", "position": 14}, {"session_key": 9566, "meeting_key": 1241, "driver_number": 23, "date": "2024-07-21T13:13:11.800000+00:00", "position": 13}, {"session_key": 9566, "meeting_key": 1241, "driver_number": 63, "date": "2024-07-21T13:13:11.800000+00:00", "position": 12}, {"session_key": 9566, "meeting_key": 1241, "driver_number": 2, "date": "2024-07-21T13:13:13.212000+00:00", "position": 13}, {"session_key": 9566, "meeting_key": 1241, "driver_number": 20, "date": "2024-07-21T13:13:13.212000+00:00", "position": 15}, {"session_key": 9566, "meeting_key": 1241, "driver_number": 23, "date": "2024-07-21T13:13:13.212000+00:00", "position": 14}, {"session_key": 9566, "meeting_key": 1241, "driver_number": 11, "date": "2024-07-21T13:13:13.884000+00:00", "position": 14}, {"session_key": 9566, "meeting_key": 1241, "driver_number": 20, "date": "2024-07-21T13:13:13.884000+00:00", "position": 16}, {"session_key": 9566, "meeting_key": 1241, "driver_number": 23, "date": "2024-07-21T13:13:13.884000+00:00", "position": 15}, {"session_key": 9566, "meeting_key": 1241, "driver_number": 10, "date": "2024-07-21T13:13:15.443000+00:00", "position": 15}, {"session_key": 9566, "meeting_key": 1241, "driver_number": 20, "date": "2024-07-21T13:13:15.443000+00:00", "position": 17}, {"session_key": 9566, "meeting_key": 1241, "driver_number": 23, "date": "2024-07-21T13:13:15.443000+00:00", "position": 16}, {"session_key": 9566, "meeting_key": 1241, "driver_number": 24, "date": "2024-07-21T13:13:15.443000+00:00", "position": 18}, {"session_key": 9566, "meeting_key": 1241, "driver_number": 31, "date": "2024-07-21T13:13:15.443000+00:00", "position": 19}, {"session_key": 9566, "meeting_key": 1241, "driver_number": 20, "date": "2024-07-21T13:13:17.453000+00:00", "position": 18}, {"session_key": 9566, "meeting_key": 1241, "driver_number": 23, "date": "2024-07-21T13:13:17.453000+00:00", "position": 17}, {"session_key": 9566, "meeting_key": 1241, "driver_number": 24, "date": "2024-07-21T13:13:17.453000+00:00", "position": 16}, {"session_key": 9566, "meeting_key": 1241, "driver_number": 20, "date": "2024-07-21T13:13:22.395000+00:00", "position": 19}, {"session_key": 9566, "meeting_key": 1241, "driver_number": 23, "date": "2024-07-21T13:13:22.395000+00:00", "position": 18}, {"session_key": 9566, "meeting_key": 1241, "driver_number": 27, "date": "2024-07-21T13:13:22.395000+00:00", "position": 17}, {"session_key": 9566, "meeting_key": 1241, "driver_number": 31, "date": "2024-07-21T13:13:22.395000+00:00", "position": 20}, {"session_key": 9566, "meeting_key": 1241, "driver_number": 14, "date": "2024-07-21T13:14:34.390000+00:00", "position": 9}, {"session_key": 9566, "meeting_key": 1241, "driver_number": 22, "date": "2024-07-21T13:14:34.390000+00:00", "position": 8}, {"session_key": 9566, "meeting_key": 1241, "driver_number": 3, "date": "2024-07-21T13:14:36.226000+00:00", "position": 11}, {"session_key": 9566, "meeting_key": 1241, "driver_number": 14, "date": "2024-07-21T13:14:36.226000+00:00", "position": 10}, {"session_key": 9566, "meeting_key": 1241, "driver_number": 77, "date": "2024-07-21T13:14:36.226000+00:00", "position": 9}, {"session_key": 9566, "meeting_key": 1241, "driver_number": 3, "date": "2024-07-21T13:14:36.944000+00:00", "position": 12}, {"session_key": 9566, "meeting_key": 1241, "driver_number": 14, "date": "2024-07-21T13:14:36.944000+00:00", "position": 11}, {"session_key": 9566, "meeting_key": 1241, "driver_number": 63, "date": "2024-07-21T13:14:36.944000+00:00", "position": 10}, {"session_key": 9566, "meeting_key": 1241, "driver_number": 2, "date": "2024-07-21T13:14:38.892000+00:00", "position": 14}, {"session_key": 9566, "meeting_key": 1241, "driver_number": 3, "date": "2024-07-21T13:14:38.892000+00:00", "position": 13}, {"session_key": 9566, "meeting_key": 1241, "driver_number": 11, "date": "2024-07-21T13:14:38.892000+00:00", "position": 11}, {"session_key": 9566, "meeting_key": 1241, "driver_number": 14, "date": "2024-07-21T13:14:38.892000+00:00", "position": 12}, {"session_key": 9566, "meeting_key": 1241, "driver_number": 2, "date": "2024-07-21T13:14:40.636000+00:00", "position": 12}, {"session_key": 9566, "meeting_key": 1241, "driver_number": 3, "date": "2024-07-21T13:14:40.636000+00:00", "position": 14}, {"session_key": 9566, "meeting_key": 1241, "driver_number": 14, "date": "2024-07-21T13:14:40.636000+00:00", "position": 13}, {"session_key": 9566, "meeting_key": 1241, "driver_number": 3, "date": "2024-07-21T13:14:41.481000+00:00", "position": 15}, {"session_key": 9566, "meeting_key": 1241, "driver_number": 10, "date": "2024-07-21T13:14:41.481000+00:00", "position": 13}, {"session_key": 9566, "meeting_key": 1241, "driver_number": 14, "date": "2024-07-21T13:14:41.481000+00:00", "position": 14}, {"session_key": 9566, "meeting_key": 1241, "driver_number": 3, "date": "2024-07-21T13:14:47.063000+00:00", "position": 16}, {"session_key": 9566, "meeting_key": 1241, "driver_number": 14, "date": "2024-07-21T13:14:47.063000+00:00", "position": 15}, {"session_key": 9566, "meeting_key": 1241, "driver_number": 24, "date": "2024-07-21T13:14:47.063000+00:00", "position": 17}, {"session_key": 9566, "meeting_key": 1241, "driver_number": 27, "date": "2024-07-21T13:14:47.063000+00:00", "position": 14}, {"session_key": 9566, "meeting_key": 1241, "driver_number": 3, "date": "2024-07-21T13:14:52.126000+00:00", "position": 17}, {"session_key": 9566, "meeting_key": 1241, "driver_number": 23, "date": "2024-07-21T13:14:52.126000+00:00", "position": 16}, {"session_key": 9566, "meeting_key": 1241, "driver_number": 24, "date": "2024-07-21T13:14:52.126000+00:00", "position": 18}, {"session_key": 9566, "meeting_key": 1241, "driver_number": 3, "date": "2024-07-21T13:14:53.142000+00:00", "position": 18}, {"session_key": 9566, "meeting_key": 1241, "driver_number": 20, "date": "2024-07-21T13:14:53.142000+00:00", "position": 17}, {"session_key": 9566, "meeting_key": 1241, "driver_number": 24, "date": "2024-07-21T13:14:53.142000+00:00", "position": 19}, {"session_key": 9566, "meeting_key": 1241, "driver_number": 24, "date": "2024-07-21T13:14:55.498000+00:00", "position": 20}, {"session_key": 9566, "meeting_key": 1241, "driver_number": 31, "date": "2024-07-21T13:14:55.498000+00:00", "position": 19}, {"session_key": 9566, "meeting_key": 1241, "driver_number": 2, "date": "2024-07-21T13:16:06.763000+00:00", "position": 13}, {"session_key": 9566, "meeting_key": 1241, "driver_number": 10, "date": "2024-07-21T13:16:06.763000+00:00", "position": 12}, {"session_key": 9566, "meeting_key": 1241, "driver_number": 2, "date": "2024-07-21T13:16:12.461000+00:00", "position": 14}, {"session_key": 9566, "meeting_key": 1241, "driver_number": 27, "date": "2024-07-21T13:16:12.461000+00:00", "position": 13}, {"session_key": 9566, "meeting_key": 1241, "driver_number": 2, "date": "2024-07-21T13:16:15.964000+00:00", "position": 15}, {"session_key": 9566, "meeting_key": 1241, "driver_number": 14, "date": "2024-07-21T13:16:15.964000+00:00", "position": 14}, {"session_key": 9566, "meeting_key": 1241, "driver_number": 2, "date": "2024-07-21T13:16:17.065000+00:00", "position": 16}, {"session_key": 9566, "meeting_key": 1241, "driver_number": 23, "date": "2024-07-21T13:16:17.065000+00:00", "position": 15}, {"session_key": 9566, "meeting_key": 1241, "driver_number": 2, "date": "2024-07-21T13:16:18.037000+00:00", "position": 17}, {"session_key": 9566, "meeting_key": 1241, "driver_number": 20, "date": "2024-07-21T13:16:18.037000+00:00", "position": 16}, {"session_key": 9566, "meeting_key": 1241, "driver_number": 2, "date": "2024-07-21T13:16:18.425000+00:00", "position": 18}, {"session_key": 9566, "meeting_key": 1241, "driver_number": 3, "date": "2024-07-21T13:16:18.425000+00:00", "position": 17}, {"session_key": 9566, "meeting_key": 1241, "driver_number": 2, "date": "2024-07-21T13:16:20.183000+00:00", "position": 19}, {"session_key": 9566, "meeting_key": 1241, "driver_number": 31, "date": "2024-07-21T13:16:20.183000+00:00", "position": 18}, {"session_key": 9566, "meeting_key": 1241, "driver_number": 18, "date": "2024-07-21T13:23:03.670000+00:00", "position": 8}, {"session_key": 9566, "meeting_key": 1241, "driver_number": 22, "date": "2024-07-21T13:23:03.670000+00:00", "position": 7}, {"session_key": 9566, "meeting_key": 1241, "driver_number": 18, "date": "2024-07-21T13:24:32.324000+00:00", "position": 9}, {"session_key": 9566, "meeting_key": 1241, "driver_number": 77, "date": "2024-07-21T13:24:32.324000+00:00", "position": 8}, {"session_key": 9566, "meeting_key": 1241, "driver_number": 18, "date": "2024-07-21T13:24:33.539000+00:00", "position": 10}, {"session_key": 9566, "meeting_key": 1241, "driver_number": 63, "date": "2024-07-21T13:24:33.539000+00:00", "position": 9}, {"session_key": 9566, "meeting_key": 1241, "driver_number": 11, "date": "2024-07-21T13:24:34.577000+00:00", "position": 10}, {"session_key": 9566, "meeting_key": 1241, "driver_number": 18, "date": "2024-07-21T13:24:34.577000+00:00", "position": 11}, {"session_key": 9566, "meeting_key": 1241, "driver_number": 10, "date": "2024-07-21T13:24:40.588000+00:00", "position": 11}, {"session_key": 9566, "meeting_key": 1241, "driver_number": 18, "date": "2024-07-21T13:24:40.588000+00:00", "position": 12}, {"session_key": 9566, "meeting_key": 1241, "driver_number": 18, "date": "2024-07-21T13:24:42.730000+00:00", "position": 13}, {"session_key": 9566, "meeting_key": 1241, "driver_number": 27, "date": "2024-07-21T13:24:42.730000+00:00", "position": 12}, {"session_key": 9566, "meeting_key": 1241, "driver_number": 14, "date": "2024-07-21T13:24:46.332000+00:00", "position": 13}, {"session_key": 9566, "meeting_key": 1241, "driver_number": 18, "date": "2024-07-21T13:24:46.332000+00:00", "position": 14}, {"session_key": 9566, "meeting_key": 1241, "driver_number": 18, "date": "2024-07-21T13:24:47.233000+00:00", "position": 15}, {"session_key": 9566, "meeting_key": 1241, "driver_number": 23, "date": "2024-07-21T13:24:47.233000+00:00", "position": 14}, {"session_key": 9566, "meeting_key": 1241, "driver_number": 18, "date": "2024-07-21T13:24:48.729000+00:00", "position": 16}, {"session_key": 9566, "meeting_key": 1241, "driver_number": 20, "date": "2024-07-21T13:24:48.729000+00:00", "position": 15}, {"session_key": 9566, "meeting_key": 1241, "driver_number": 16, "date": "2024-07-21T13:25:38.257000+00:00", "position": 4}, {"session_key": 9566, "meeting_key": 1241, "driver_number": 44, "date": "2024-07-21T13:25:38.257000+00:00", "position": 5}, {"session_key": 9566, "meeting_key": 1241, "driver_number": 63, "date": "2024-07-21T13:25:58.832000+00:00", "position": 8}, {"session_key": 9566, "meeting_key": 1241, "driver_number": 77, "date": "2024-07-21T13:25:58.832000+00:00", "position": 9}, {"session_key": 9566, "meeting_key": 1241, "driver_number": 11, "date": "2024-07-21T13:25:59.847000+00:00", "position": 9}, {"session_key": 9566, "meeting_key": 1241, "driver_number": 77, "date": "2024-07-21T13:25:59.847000+00:00", "position": 10}, {"session_key": 9566, "meeting_key": 1241, "driver_number": 18, "date": "2024-07-21T13:26:13.449000+00:00", "position": 15}, {"session_key": 9566, "meeting_key": 1241, "driver_number": 20, "date": "2024-07-21T13:26:13.449000+00:00", "position": 16}, {"session_key": 9566, "meeting_key": 1241, "driver_number": 44, "date": "2024-07-21T13:27:07.543000+00:00", "position": 6}, {"session_key": 9566, "meeting_key": 1241, "driver_number": 55, "date": "2024-07-21T13:27:07.543000+00:00", "position": 5}, {"session_key": 9566, "meeting_key": 1241, "driver_number": 22, "date": "2024-07-21T13:27:18.478000+00:00", "position": 6}, {"session_key": 9566, "meeting_key": 1241, "driver_number": 44, "date": "2024-07-21T13:27:18.478000+00:00", "position": 7}, {"session_key": 9566, "meeting_key": 1241, "driver_number": 10, "date": "2024-07-21T13:27:32.006000+00:00", "position": 10}, {"session_key": 9566, "meeting_key": 1241, "driver_number": 77, "date": "2024-07-21T13:27:32.006000+00:00", "position": 11}, {"session_key": 9566, "meeting_key": 1241, "driver_number": 27, "date": "2024-07-21T13:27:34.644000+00:00", "position": 11}, {"session_key": 9566, "meeting_key": 1241, "driver_number": 77, "date": "2024-07-21T13:27:34.644000+00:00", "position": 12}, {"session_key": 9566, "meeting_key": 1241, "driver_number": 14, "date": "2024-07-21T13:27:37.598000+00:00", "position": 12}, {"session_key": 9566, "meeting_key": 1241, "driver_number": 77, "date": "2024-07-21T13:27:37.598000+00:00", "position": 13}, {"session_key": 9566, "meeting_key": 1241, "driver_number": 23, "date": "2024-07-21T13:27:38.690000+00:00", "position": 13}, {"session_key": 9566, "meeting_key": 1241, "driver_number": 77, "date": "2024-07-21T13:27:38.690000+00:00", "position": 14}, {"session_key": 9566, "meeting_key": 1241, "driver_number": 18, "date": "2024-07-21T13:27:39.064000+00:00", "position": 14}, {"session_key": 9566, "meeting_key": 1241, "driver_number": 77, "date": "2024-07-21T13:27:39.064000+00:00", "position": 15}, {"session_key": 9566, "meeting_key": 1241, "driver_number": 20, "date": "2024-07-21T13:27:40.872000+00:00", "position": 15}, {"session_key": 9566, "meeting_key": 1241, "driver_number": 77, "date": "2024-07-21T13:27:40.872000+00:00", "position": 16}, {"session_key": 9566, "meeting_key": 1241, "driver_number": 3, "date": "2024-07-21T13:27:41.423000+00:00", "position": 16}, {"session_key": 9566, "meeting_key": 1241, "driver_number": 77, "date": "2024-07-21T13:27:41.423000+00:00", "position": 17}, {"session_key": 9566, "meeting_key": 1241, "driver_number": 31, "date": "2024-07-21T13:27:42.856000+00:00", "position": 17}, {"session_key": 9566, "meeting_key": 1241, "driver_number": 77, "date": "2024-07-21T13:27:42.856000+00:00", "position": 18}, {"session_key": 9566, "meeting_key": 1241, "driver_number": 1, "date": "2024-07-21T13:28:24.363000+00:00", "position": 2}, {"session_key": 9566, "meeting_key": 1241, "driver_number": 4, "date": "2024-07-21T13:28:24.363000+00:00", "position": 3}, {"session_key": 9566, "meeting_key": 1241, "driver_number": 4, "date": "2024-07-21T13:28:27.770000+00:00", "position": 4}, {"session_key": 9566, "meeting_key": 1241, "driver_number": 16, "date": "2024-07-21T13:28:27.770000+00:00", "position": 3}, {"session_key": 9566, "meeting_key": 1241, "driver_number": 4, "date": "2024-07-21T13:28:32.295000+00:00", "position": 5}, {"session_key": 9566, "meeting_key": 1241, "driver_number": 55, "date": "2024-07-21T13:28:32.295000+00:00", "position": 4}, {"session_key": 9566, "meeting_key": 1241, "driver_number": 22, "date": "2024-07-21T13:28:42.326000+00:00", "position": 7}, {"session_key": 9566, "meeting_key": 1241, "driver_number": 44, "date": "2024-07-21T13:28:42.326000+00:00", "position": 6}, {"session_key": 9566, "meeting_key": 1241, "driver_number": 18, "date": "2024-07-21T13:29:04.057000+00:00", "position": 13}, {"session_key": 9566, "meeting_key": 1241, "driver_number": 23, "date": "2024-07-21T13:29:04.057000+00:00", "position": 14}, {"session_key": 9566, "meeting_key": 1241, "driver_number": 1, "date": "2024-07-21T13:29:48.861000+00:00", "position": 1}, {"session_key": 9566, "meeting_key": 1241, "driver_number": 81, "date": "2024-07-21T13:29:48.861000+00:00", "position": 2}, {"session_key": 9566, "meeting_key": 1241, "driver_number": 16, "date": "2024-07-21T13:29:52.371000+00:00", "position": 2}, {"session_key": 9566, "meeting_key": 1241, "driver_number": 81, "date": "2024-07-21T13:29:52.371000+00:00", "position": 3}, {"session_key": 9566, "meeting_key": 1241, "driver_number": 55, "date": "2024-07-21T13:29:57.137000+00:00", "position": 3}, {"session_key": 9566, "meeting_key": 1241, "driver_number": 81, "date": "2024-07-21T13:29:57.137000+00:00", "position": 4}, {"session_key": 9566, "meeting_key": 1241, "driver_number": 31, "date": "2024-07-21T13:30:33.963000+00:00", "position": 18}, {"session_key": 9566, "meeting_key": 1241, "driver_number": 77, "date": "2024-07-21T13:30:33.963000+00:00", "position": 17}, {"session_key": 9566, "meeting_key": 1241, "driver_number": 55, "date": "2024-07-21T13:32:47.729000+00:00", "position": 4}, {"session_key": 9566, "meeting_key": 1241, "driver_number": 81, "date": "2024-07-21T13:32:47.729000+00:00", "position": 3}, {"session_key": 9566, "meeting_key": 1241, "driver_number": 1, "date": "2024-07-21T13:34:05.880000+00:00", "position": 2}, {"session_key": 9566, "meeting_key": 1241, "driver_number": 16, "date": "2024-07-21T13:34:05.880000+00:00", "position": 1}, {"session_key": 9566, "meeting_key": 1241, "driver_number": 1, "date": "2024-07-21T13:34:11.057000+00:00", "position": 3}, {"session_key": 9566, "meeting_key": 1241, "driver_number": 81, "date": "2024-07-21T13:34:11.057000+00:00", "position": 2}, {"session_key": 9566, "meeting_key": 1241, "driver_number": 1, "date": "2024-07-21T13:34:13.580000+00:00", "position": 4}, {"session_key": 9566, "meeting_key": 1241, "driver_number": 4, "date": "2024-07-21T13:34:13.580000+00:00", "position": 3}, {"session_key": 9566, "meeting_key": 1241, "driver_number": 55, "date": "2024-07-21T13:34:13.580000+00:00", "position": 5}, {"session_key": 9566, "meeting_key": 1241, "driver_number": 1, "date": "2024-07-21T13:34:15.400000+00:00", "position": 5}, {"session_key": 9566, "meeting_key": 1241, "driver_number": 44, "date": "2024-07-21T13:34:15.400000+00:00", "position": 4}, {"session_key": 9566, "meeting_key": 1241, "driver_number": 55, "date": "2024-07-21T13:34:15.400000+00:00", "position": 6}, {"session_key": 9566, "meeting_key": 1241, "driver_number": 22, "date": "2024-07-21T13:34:26.247000+00:00", "position": 6}, {"session_key": 9566, "meeting_key": 1241, "driver_number": 55, "date": "2024-07-21T13:34:26.247000+00:00", "position": 7}, {"session_key": 9566, "meeting_key": 1241, "driver_number": 55, "date": "2024-07-21T13:34:28.369000+00:00", "position": 8}, {"session_key": 9566, "meeting_key": 1241, "driver_number": 63, "date": "2024-07-21T13:34:28.369000+00:00", "position": 7}, {"session_key": 9566, "meeting_key": 1241, "driver_number": 11, "date": "2024-07-21T13:34:29.778000+00:00", "position": 8}, {"session_key": 9566, "meeting_key": 1241, "driver_number": 55, "date": "2024-07-21T13:34:29.778000+00:00", "position": 9}, {"session_key": 9566, "meeting_key": 1241, "driver_number": 16, "date": "2024-07-21T13:36:57.139000+00:00", "position": 2}, {"session_key": 9566, "meeting_key": 1241, "driver_number": 81, "date": "2024-07-21T13:36:57.139000+00:00", "position": 1}, {"session_key": 9566, "meeting_key": 1241, "driver_number": 4, "date": "2024-07-21T13:37:00.406000+00:00", "position": 2}, {"session_key": 9566, "meeting_key": 1241, "driver_number": 16, "date": "2024-07-21T13:37:00.406000+00:00", "position": 3}, {"session_key": 9566, "meeting_key": 1241, "driver_number": 16, "date": "2024-07-21T13:37:02.726000+00:00", "position": 4}, {"session_key": 9566, "meeting_key": 1241, "driver_number": 44, "date": "2024-07-21T13:37:02.726000+00:00", "position": 3}, {"session_key": 9566, "meeting_key": 1241, "driver_number": 1, "date": "2024-07-21T13:37:07.636000+00:00", "position": 4}, {"session_key": 9566, "meeting_key": 1241, "driver_number": 16, "date": "2024-07-21T13:37:07.636000+00:00", "position": 5}, {"session_key": 9566, "meeting_key": 1241, "driver_number": 11, "date": "2024-07-21T13:37:19.084000+00:00", "position": 9}, {"session_key": 9566, "meeting_key": 1241, "driver_number": 55, "date": "2024-07-21T13:37:19.084000+00:00", "position": 8}, {"session_key": 9566, "meeting_key": 1241, "driver_number": 55, "date": "2024-07-21T13:38:43.741000+00:00", "position": 7}, {"session_key": 9566, "meeting_key": 1241, "driver_number": 63, "date": "2024-07-21T13:38:43.741000+00:00", "position": 8}, {"session_key": 9566, "meeting_key": 1241, "driver_number": 22, "date": "2024-07-21T13:40:07.714000+00:00", "position": 7}, {"session_key": 9566, "meeting_key": 1241, "driver_number": 55, "date": "2024-07-21T13:40:07.714000+00:00", "position": 6}, {"session_key": 9566, "meeting_key": 1241, "driver_number": 14, "date": "2024-07-21T13:41:50.745000+00:00", "position": 11}, {"session_key": 9566, "meeting_key": 1241, "driver_number": 27, "date": "2024-07-21T13:41:50.745000+00:00", "position": 12}, {"session_key": 9566, "meeting_key": 1241, "driver_number": 10, "date": "2024-07-21T13:43:16.882000+00:00", "position": 11}, {"session_key": 9566, "meeting_key": 1241, "driver_number": 14, "date": "2024-07-21T13:43:16.882000+00:00", "position": 10}, {"session_key": 9566, "meeting_key": 1241, "driver_number": 10, "date": "2024-07-21T13:43:17.997000+00:00", "position": 12}, {"session_key": 9566, "meeting_key": 1241, "driver_number": 18, "date": "2024-07-21T13:43:17.997000+00:00", "position": 11}, {"session_key": 9566, "meeting_key": 1241, "driver_number": 27, "date": "2024-07-21T13:43:17.997000+00:00", "position": 13}, {"session_key": 9566, "meeting_key": 1241, "driver_number": 3, "date": "2024-07-21T13:43:23.712000+00:00", "position": 17}, {"session_key": 9566, "meeting_key": 1241, "driver_number": 77, "date": "2024-07-21T13:43:23.712000+00:00", "position": 16}, {"session_key": 9566, "meeting_key": 1241, "driver_number": 22, "date": "2024-07-21T13:44:28.578000+00:00", "position": 8}, {"session_key": 9566, "meeting_key": 1241, "driver_number": 63, "date": "2024-07-21T13:44:28.578000+00:00", "position": 7}, {"session_key": 9566, "meeting_key": 1241, "driver_number": 11, "date": "2024-07-21T13:44:40.678000+00:00", "position": 10}, {"session_key": 9566, "meeting_key": 1241, "driver_number": 14, "date": "2024-07-21T13:44:40.678000+00:00", "position": 9}, {"session_key": 9566, "meeting_key": 1241, "driver_number": 11, "date": "2024-07-21T13:44:42.366000+00:00", "position": 11}, {"session_key": 9566, "meeting_key": 1241, "driver_number": 18, "date": "2024-07-21T13:44:42.366000+00:00", "position": 10}, {"session_key": 9566, "meeting_key": 1241, "driver_number": 10, "date": "2024-07-21T13:44:47.672000+00:00", "position": 13}, {"session_key": 9566, "meeting_key": 1241, "driver_number": 11, "date": "2024-07-21T13:44:47.672000+00:00", "position": 12}, {"session_key": 9566, "meeting_key": 1241, "driver_number": 27, "date": "2024-07-21T13:44:47.672000+00:00", "position": 11}, {"session_key": 9566, "meeting_key": 1241, "driver_number": 10, "date": "2024-07-21T13:44:48.391000+00:00", "position": 14}, {"session_key": 9566, "meeting_key": 1241, "driver_number": 11, "date": "2024-07-21T13:44:48.391000+00:00", "position": 13}, {"session_key": 9566, "meeting_key": 1241, "driver_number": 20, "date": "2024-07-21T13:44:48.391000+00:00", "position": 12}, {"session_key": 9566, "meeting_key": 1241, "driver_number": 23, "date": "2024-07-21T13:44:48.391000+00:00", "position": 15}, {"session_key": 9566, "meeting_key": 1241, "driver_number": 10, "date": "2024-07-21T13:44:48.897000+00:00", "position": 15}, {"session_key": 9566, "meeting_key": 1241, "driver_number": 11, "date": "2024-07-21T13:44:48.897000+00:00", "position": 14}, {"session_key": 9566, "meeting_key": 1241, "driver_number": 23, "date": "2024-07-21T13:44:48.897000+00:00", "position": 16}, {"session_key": 9566, "meeting_key": 1241, "driver_number": 77, "date": "2024-07-21T13:44:48.897000+00:00", "position": 13}, {"session_key": 9566, "meeting_key": 1241, "driver_number": 10, "date": "2024-07-21T13:44:49.186000+00:00", "position": 16}, {"session_key": 9566, "meeting_key": 1241, "driver_number": 23, "date": "2024-07-21T13:44:49.186000+00:00", "position": 15}, {"session_key": 9566, "meeting_key": 1241, "driver_number": 3, "date": "2024-07-21T13:44:51.588000+00:00", "position": 18}, {"session_key": 9566, "meeting_key": 1241, "driver_number": 10, "date": "2024-07-21T13:44:51.588000+00:00", "position": 17}, {"session_key": 9566, "meeting_key": 1241, "driver_number": 31, "date": "2024-07-21T13:44:51.588000+00:00", "position": 16}, {"session_key": 9566, "meeting_key": 1241, "driver_number": 2, "date": "2024-07-21T13:44:52.264000+00:00", "position": 17}, {"session_key": 9566, "meeting_key": 1241, "driver_number": 3, "date": "2024-07-21T13:44:52.264000+00:00", "position": 19}, {"session_key": 9566, "meeting_key": 1241, "driver_number": 10, "date": "2024-07-21T13:44:52.264000+00:00", "position": 18}, {"session_key": 9566, "meeting_key": 1241, "driver_number": 3, "date": "2024-07-21T13:44:55.698000+00:00", "position": 20}, {"session_key": 9566, "meeting_key": 1241, "driver_number": 10, "date": "2024-07-21T13:44:55.698000+00:00", "position": 19}, {"session_key": 9566, "meeting_key": 1241, "driver_number": 24, "date": "2024-07-21T13:44:55.698000+00:00", "position": 18}, {"session_key": 9566, "meeting_key": 1241, "driver_number": 14, "date": "2024-07-21T13:46:05.036000+00:00", "position": 8}, {"session_key": 9566, "meeting_key": 1241, "driver_number": 22, "date": "2024-07-21T13:46:05.036000+00:00", "position": 9}, {"session_key": 9566, "meeting_key": 1241, "driver_number": 18, "date": "2024-07-21T13:46:06.488000+00:00", "position": 9}, {"session_key": 9566, "meeting_key": 1241, "driver_number": 22, "date": "2024-07-21T13:46:06.488000+00:00", "position": 10}, {"session_key": 9566, "meeting_key": 1241, "driver_number": 20, "date": "2024-07-21T13:46:14.166000+00:00", "position": 11}, {"session_key": 9566, "meeting_key": 1241, "driver_number": 27, "date": "2024-07-21T13:46:14.166000+00:00", "position": 12}, {"session_key": 9566, "meeting_key": 1241, "driver_number": 11, "date": "2024-07-21T13:46:14.432000+00:00", "position": 12}, {"session_key": 9566, "meeting_key": 1241, "driver_number": 27, "date": "2024-07-21T13:46:14.432000+00:00", "position": 13}, {"session_key": 9566, "meeting_key": 1241, "driver_number": 77, "date": "2024-07-21T13:46:14.432000+00:00", "position": 14}, {"session_key": 9566, "meeting_key": 1241, "driver_number": 27, "date": "2024-07-21T13:46:15.468000+00:00", "position": 14}, {"session_key": 9566, "meeting_key": 1241, "driver_number": 77, "date": "2024-07-21T13:46:15.468000+00:00", "position": 13}, {"session_key": 9566, "meeting_key": 1241, "driver_number": 2, "date": "2024-07-21T13:46:18.209000+00:00", "position": 14}, {"session_key": 9566, "meeting_key": 1241, "driver_number": 23, "date": "2024-07-21T13:46:18.209000+00:00", "position": 16}, {"session_key": 9566, "meeting_key": 1241, "driver_number": 27, "date": "2024-07-21T13:46:18.209000+00:00", "position": 15}, {"session_key": 9566, "meeting_key": 1241, "driver_number": 31, "date": "2024-07-21T13:46:18.209000+00:00", "position": 17}, {"session_key": 9566, "meeting_key": 1241, "driver_number": 23, "date": "2024-07-21T13:46:20.146000+00:00", "position": 17}, {"session_key": 9566, "meeting_key": 1241, "driver_number": 27, "date": "2024-07-21T13:46:20.146000+00:00", "position": 16}, {"session_key": 9566, "meeting_key": 1241, "driver_number": 31, "date": "2024-07-21T13:46:20.146000+00:00", "position": 15}, {"session_key": 9566, "meeting_key": 1241, "driver_number": 23, "date": "2024-07-21T13:46:21.353000+00:00", "position": 18}, {"session_key": 9566, "meeting_key": 1241, "driver_number": 24, "date": "2024-07-21T13:46:21.353000+00:00", "position": 16}, {"session_key": 9566, "meeting_key": 1241, "driver_number": 27, "date": "2024-07-21T13:46:21.353000+00:00", "position": 17}, {"session_key": 9566, "meeting_key": 1241, "driver_number": 10, "date": "2024-07-21T13:46:24.121000+00:00", "position": 17}, {"session_key": 9566, "meeting_key": 1241, "driver_number": 23, "date": "2024-07-21T13:46:24.121000+00:00", "position": 19}, {"session_key": 9566, "meeting_key": 1241, "driver_number": 27, "date": "2024-07-21T13:46:24.121000+00:00", "position": 18}, {"session_key": 9566, "meeting_key": 1241, "driver_number": 3, "date": "2024-07-21T13:46:28.141000+00:00", "position": 18}, {"session_key": 9566, "meeting_key": 1241, "driver_number": 23, "date": "2024-07-21T13:46:28.141000+00:00", "position": 20}, {"session_key": 9566, "meeting_key": 1241, "driver_number": 27, "date": "2024-07-21T13:46:28.141000+00:00", "position": 19}, {"session_key": 9566, "meeting_key": 1241, "driver_number": 11, "date": "2024-07-21T13:47:37.131000+00:00", "position": 11}, {"session_key": 9566, "meeting_key": 1241, "driver_number": 20, "date": "2024-07-21T13:47:37.131000+00:00", "position": 12}, {"session_key": 9566, "meeting_key": 1241, "driver_number": 24, "date": "2024-07-21T13:47:46.971000+00:00", "position": 15}, {"session_key": 9566, "meeting_key": 1241, "driver_number": 31, "date": "2024-07-21T13:47:46.971000+00:00", "position": 16}, {"session_key": 9566, "meeting_key": 1241, "driver_number": 10, "date": "2024-07-21T13:47:47.575000+00:00", "position": 16}, {"session_key": 9566, "meeting_key": 1241, "driver_number": 31, "date": "2024-07-21T13:47:47.575000+00:00", "position": 17}, {"session_key": 9566, "meeting_key": 1241, "driver_number": 3, "date": "2024-07-21T13:47:51.245000+00:00", "position": 17}, {"session_key": 9566, "meeting_key": 1241, "driver_number": 31, "date": "2024-07-21T13:47:51.245000+00:00", "position": 18}, {"session_key": 9566, "meeting_key": 1241, "driver_number": 27, "date": "2024-07-21T13:47:54.383000+00:00", "position": 18}, {"session_key": 9566, "meeting_key": 1241, "driver_number": 31, "date": "2024-07-21T13:47:54.383000+00:00", "position": 19}, {"session_key": 9566, "meeting_key": 1241, "driver_number": 23, "date": "2024-07-21T13:47:56.728000+00:00", "position": 19}, {"session_key": 9566, "meeting_key": 1241, "driver_number": 31, "date": "2024-07-21T13:47:56.728000+00:00", "position": 20}, {"session_key": 9566, "meeting_key": 1241, "driver_number": 10, "date": "2024-07-21T13:49:11.076000+00:00", "position": 15}, {"session_key": 9566, "meeting_key": 1241, "driver_number": 24, "date": "2024-07-21T13:49:11.076000+00:00", "position": 16}, {"session_key": 9566, "meeting_key": 1241, "driver_number": 11, "date": "2024-07-21T13:50:22.770000+00:00", "position": 10}, {"session_key": 9566, "meeting_key": 1241, "driver_number": 22, "date": "2024-07-21T13:50:22.770000+00:00", "position": 11}, {"session_key": 9566, "meeting_key": 1241, "driver_number": 14, "date": "2024-07-21T13:51:42.635000+00:00", "position": 7}, {"session_key": 9566, "meeting_key": 1241, "driver_number": 63, "date": "2024-07-21T13:51:42.635000+00:00", "position": 8}, {"session_key": 9566, "meeting_key": 1241, "driver_number": 18, "date": "2024-07-21T13:51:44.867000+00:00", "position": 8}, {"session_key": 9566, "meeting_key": 1241, "driver_number": 63, "date": "2024-07-21T13:51:44.867000+00:00", "position": 9}, {"session_key": 9566, "meeting_key": 1241, "driver_number": 11, "date": "2024-07-21T13:51:45.447000+00:00", "position": 9}, {"session_key": 9566, "meeting_key": 1241, "driver_number": 63, "date": "2024-07-21T13:51:45.447000+00:00", "position": 10}, {"session_key": 9566, "meeting_key": 1241, "driver_number": 22, "date": "2024-07-21T13:51:48.726000+00:00", "position": 10}, {"session_key": 9566, "meeting_key": 1241, "driver_number": 63, "date": "2024-07-21T13:51:48.726000+00:00", "position": 11}, {"session_key": 9566, "meeting_key": 1241, "driver_number": 20, "date": "2024-07-21T13:51:57.656000+00:00", "position": 13}, {"session_key": 9566, "meeting_key": 1241, "driver_number": 77, "date": "2024-07-21T13:51:57.656000+00:00", "position": 12}, {"session_key": 9566, "meeting_key": 1241, "driver_number": 2, "date": "2024-07-21T13:52:04.480000+00:00", "position": 15}, {"session_key": 9566, "meeting_key": 1241, "driver_number": 3, "date": "2024-07-21T13:52:04.480000+00:00", "position": 14}, {"session_key": 9566, "meeting_key": 1241, "driver_number": 10, "date": "2024-07-21T13:52:04.480000+00:00", "position": 16}, {"session_key": 9566, "meeting_key": 1241, "driver_number": 24, "date": "2024-07-21T13:52:04.480000+00:00", "position": 17}, {"session_key": 9566, "meeting_key": 1241, "driver_number": 2, "date": "2024-07-21T13:52:08.240000+00:00", "position": 16}, {"session_key": 9566, "meeting_key": 1241, "driver_number": 10, "date": "2024-07-21T13:52:08.240000+00:00", "position": 17}, {"session_key": 9566, "meeting_key": 1241, "driver_number": 24, "date": "2024-07-21T13:52:08.240000+00:00", "position": 15}, {"session_key": 9566, "meeting_key": 1241, "driver_number": 2, "date": "2024-07-21T13:52:08.455000+00:00", "position": 17}, {"session_key": 9566, "meeting_key": 1241, "driver_number": 10, "date": "2024-07-21T13:52:08.455000+00:00", "position": 18}, {"session_key": 9566, "meeting_key": 1241, "driver_number": 27, "date": "2024-07-21T13:52:08.455000+00:00", "position": 16}, {"session_key": 9566, "meeting_key": 1241, "driver_number": 2, "date": "2024-07-21T13:52:08.999000+00:00", "position": 18}, {"session_key": 9566, "meeting_key": 1241, "driver_number": 10, "date": "2024-07-21T13:52:08.999000+00:00", "position": 19}, {"session_key": 9566, "meeting_key": 1241, "driver_number": 23, "date": "2024-07-21T13:52:08.999000+00:00", "position": 17}, {"session_key": 9566, "meeting_key": 1241, "driver_number": 2, "date": "2024-07-21T13:52:18.470000+00:00", "position": 19}, {"session_key": 9566, "meeting_key": 1241, "driver_number": 10, "date": "2024-07-21T13:52:18.470000+00:00", "position": 20}, {"session_key": 9566, "meeting_key": 1241, "driver_number": 31, "date": "2024-07-21T13:52:18.470000+00:00", "position": 18}, {"session_key": 9566, "meeting_key": 1241, "driver_number": 3, "date": "2024-07-21T13:53:28.070000+00:00", "position": 13}, {"session_key": 9566, "meeting_key": 1241, "driver_number": 20, "date": "2024-07-21T13:53:28.070000+00:00", "position": 14}, {"session_key": 9566, "meeting_key": 1241, "driver_number": 20, "date": "2024-07-21T13:53:32.042000+00:00", "position": 15}, {"session_key": 9566, "meeting_key": 1241, "driver_number": 24, "date": "2024-07-21T13:53:32.042000+00:00", "position": 16}, {"session_key": 9566, "meeting_key": 1241, "driver_number": 27, "date": "2024-07-21T13:53:32.042000+00:00", "position": 14}, {"session_key": 9566, "meeting_key": 1241, "driver_number": 20, "date": "2024-07-21T13:53:33.767000+00:00", "position": 16}, {"session_key": 9566, "meeting_key": 1241, "driver_number": 23, "date": "2024-07-21T13:53:33.767000+00:00", "position": 15}, {"session_key": 9566, "meeting_key": 1241, "driver_number": 24, "date": "2024-07-21T13:53:33.767000+00:00", "position": 17}, {"session_key": 9566, "meeting_key": 1241, "driver_number": 20, "date": "2024-07-21T13:53:36.467000+00:00", "position": 17}, {"session_key": 9566, "meeting_key": 1241, "driver_number": 24, "date": "2024-07-21T13:53:36.467000+00:00", "position": 16}, {"session_key": 9566, "meeting_key": 1241, "driver_number": 11, "date": "2024-07-21T13:54:32.683000+00:00", "position": 8}, {"session_key": 9566, "meeting_key": 1241, "driver_number": 18, "date": "2024-07-21T13:54:32.683000+00:00", "position": 9}, {"session_key": 9566, "meeting_key": 1241, "driver_number": 11, "date": "2024-07-21T13:55:57.182000+00:00", "position": 7}, {"session_key": 9566, "meeting_key": 1241, "driver_number": 14, "date": "2024-07-21T13:55:57.182000+00:00", "position": 8}, {"session_key": 9566, "meeting_key": 1241, "driver_number": 22, "date": "2024-07-21T13:56:00.519000+00:00", "position": 11}, {"session_key": 9566, "meeting_key": 1241, "driver_number": 63, "date": "2024-07-21T13:56:00.519000+00:00", "position": 10}, {"session_key": 9566, "meeting_key": 1241, "driver_number": 20, "date": "2024-07-21T13:56:30.967000+00:00", "position": 16}, {"session_key": 9566, "meeting_key": 1241, "driver_number": 24, "date": "2024-07-21T13:56:30.967000+00:00", "position": 17}, {"session_key": 9566, "meeting_key": 1241, "driver_number": 24, "date": "2024-07-21T13:56:32.034000+00:00", "position": 18}, {"session_key": 9566, "meeting_key": 1241, "driver_number": 31, "date": "2024-07-21T13:56:32.034000+00:00", "position": 17}, {"session_key": 9566, "meeting_key": 1241, "driver_number": 2, "date": "2024-07-21T13:56:32.586000+00:00", "position": 18}, {"session_key": 9566, "meeting_key": 1241, "driver_number": 24, "date": "2024-07-21T13:56:32.586000+00:00", "position": 19}, {"session_key": 9566, "meeting_key": 1241, "driver_number": 14, "date": "2024-07-21T13:57:23.395000+00:00", "position": 9}, {"session_key": 9566, "meeting_key": 1241, "driver_number": 18, "date": "2024-07-21T13:57:23.395000+00:00", "position": 10}, {"session_key": 9566, "meeting_key": 1241, "driver_number": 63, "date": "2024-07-21T13:57:23.395000+00:00", "position": 8}, {"session_key": 9566, "meeting_key": 1241, "driver_number": 14, "date": "2024-07-21T13:57:25.778000+00:00", "position": 10}, {"session_key": 9566, "meeting_key": 1241, "driver_number": 18, "date": "2024-07-21T13:57:25.778000+00:00", "position": 9}, {"session_key": 9566, "meeting_key": 1241, "driver_number": 14, "date": "2024-07-21T13:57:27.249000+00:00", "position": 11}, {"session_key": 9566, "meeting_key": 1241, "driver_number": 22, "date": "2024-07-21T13:57:27.249000+00:00", "position": 10}, {"session_key": 9566, "meeting_key": 1241, "driver_number": 14, "date": "2024-07-21T13:57:35.916000+00:00", "position": 12}, {"session_key": 9566, "meeting_key": 1241, "driver_number": 77, "date": "2024-07-21T13:57:35.916000+00:00", "position": 11}, {"session_key": 9566, "meeting_key": 1241, "driver_number": 3, "date": "2024-07-21T13:57:39.467000+00:00", "position": 12}, {"session_key": 9566, "meeting_key": 1241, "driver_number": 14, "date": "2024-07-21T13:57:39.467000+00:00", "position": 13}, {"session_key": 9566, "meeting_key": 1241, "driver_number": 3, "date": "2024-07-21T13:59:03.740000+00:00", "position": 13}, {"session_key": 9566, "meeting_key": 1241, "driver_number": 14, "date": "2024-07-21T13:59:03.740000+00:00", "position": 12}, {"session_key": 9566, "meeting_key": 1241, "driver_number": 1, "date": "2024-07-21T13:59:28.593000+00:00", "position": 3}, {"session_key": 9566, "meeting_key": 1241, "driver_number": 44, "date": "2024-07-21T13:59:28.593000+00:00", "position": 4}, {"session_key": 9566, "meeting_key": 1241, "driver_number": 16, "date": "2024-07-21T14:00:59.203000+00:00", "position": 6}, {"session_key": 9566, "meeting_key": 1241, "driver_number": 44, "date": "2024-07-21T14:00:59.203000+00:00", "position": 5}, {"session_key": 9566, "meeting_key": 1241, "driver_number": 55, "date": "2024-07-21T14:00:59.203000+00:00", "position": 4}, {"session_key": 9566, "meeting_key": 1241, "driver_number": 14, "date": "2024-07-21T14:03:14.824000+00:00", "position": 11}, {"session_key": 9566, "meeting_key": 1241, "driver_number": 77, "date": "2024-07-21T14:03:14.824000+00:00", "position": 12}, {"session_key": 9566, "meeting_key": 1241, "driver_number": 3, "date": "2024-07-21T14:06:06.859000+00:00", "position": 12}, {"session_key": 9566, "meeting_key": 1241, "driver_number": 77, "date": "2024-07-21T14:06:06.859000+00:00", "position": 13}, {"session_key": 9566, "meeting_key": 1241, "driver_number": 18, "date": "2024-07-21T14:07:18.583000+00:00", "position": 10}, {"session_key": 9566, "meeting_key": 1241, "driver_number": 22, "date": "2024-07-21T14:07:18.583000+00:00", "position": 9}, {"session_key": 9566, "meeting_key": 1241, "driver_number": 27, "date": "2024-07-21T14:07:36.146000+00:00", "position": 13}, {"session_key": 9566, "meeting_key": 1241, "driver_number": 77, "date": "2024-07-21T14:07:36.146000+00:00", "position": 14}, {"session_key": 9566, "meeting_key": 1241, "driver_number": 23, "date": "2024-07-21T14:07:37.320000+00:00", "position": 14}, {"session_key": 9566, "meeting_key": 1241, "driver_number": 77, "date": "2024-07-21T14:07:37.320000+00:00", "position": 15}, {"session_key": 9566, "meeting_key": 1241, "driver_number": 1, "date": "2024-07-21T14:07:50.054000+00:00", "position": 2}, {"session_key": 9566, "meeting_key": 1241, "driver_number": 4, "date": "2024-07-21T14:07:50.054000+00:00", "position": 3}, {"session_key": 9566, "meeting_key": 1241, "driver_number": 4, "date": "2024-07-21T14:07:59.035000+00:00", "position": 4}, {"session_key": 9566, "meeting_key": 1241, "driver_number": 55, "date": "2024-07-21T14:07:59.035000+00:00", "position": 3}, {"session_key": 9566, "meeting_key": 1241, "driver_number": 14, "date": "2024-07-21T14:08:50.335000+00:00", "position": 10}, {"session_key": 9566, "meeting_key": 1241, "driver_number": 18, "date": "2024-07-21T14:08:50.335000+00:00", "position": 11}, {"session_key": 9566, "meeting_key": 1241, "driver_number": 3, "date": "2024-07-21T14:08:54.730000+00:00", "position": 11}, {"session_key": 9566, "meeting_key": 1241, "driver_number": 18, "date": "2024-07-21T14:08:54.730000+00:00", "position": 12}, {"session_key": 9566, "meeting_key": 1241, "driver_number": 18, "date": "2024-07-21T14:08:59.758000+00:00", "position": 13}, {"session_key": 9566, "meeting_key": 1241, "driver_number": 27, "date": "2024-07-21T14:08:59.758000+00:00", "position": 12}, {"session_key": 9566, "meeting_key": 1241, "driver_number": 18, "date": "2024-07-21T14:09:01.667000+00:00", "position": 14}, {"session_key": 9566, "meeting_key": 1241, "driver_number": 23, "date": "2024-07-21T14:09:01.667000+00:00", "position": 13}, {"session_key": 9566, "meeting_key": 1241, "driver_number": 20, "date": "2024-07-21T14:09:08.663000+00:00", "position": 15}, {"session_key": 9566, "meeting_key": 1241, "driver_number": 77, "date": "2024-07-21T14:09:08.663000+00:00", "position": 16}, {"session_key": 9566, "meeting_key": 1241, "driver_number": 31, "date": "2024-07-21T14:09:10.600000+00:00", "position": 16}, {"session_key": 9566, "meeting_key": 1241, "driver_number": 77, "date": "2024-07-21T14:09:10.600000+00:00", "position": 17}, {"session_key": 9566, "meeting_key": 1241, "driver_number": 2, "date": "2024-07-21T14:09:12.090000+00:00", "position": 17}, {"session_key": 9566, "meeting_key": 1241, "driver_number": 77, "date": "2024-07-21T14:09:12.090000+00:00", "position": 18}, {"session_key": 9566, "meeting_key": 1241, "driver_number": 4, "date": "2024-07-21T14:09:23.343000+00:00", "position": 3}, {"session_key": 9566, "meeting_key": 1241, "driver_number": 55, "date": "2024-07-21T14:09:23.343000+00:00", "position": 4}, {"session_key": 9566, "meeting_key": 1241, "driver_number": 11, "date": "2024-07-21T14:09:48.151000+00:00", "position": 8}, {"session_key": 9566, "meeting_key": 1241, "driver_number": 63, "date": "2024-07-21T14:09:48.151000+00:00", "position": 7}, {"session_key": 9566, "meeting_key": 1241, "driver_number": 18, "date": "2024-07-21T14:10:24.700000+00:00", "position": 13}, {"session_key": 9566, "meeting_key": 1241, "driver_number": 23, "date": "2024-07-21T14:10:24.700000+00:00", "position": 14}, {"session_key": 9566, "meeting_key": 1241, "driver_number": 1, "date": "2024-07-21T14:10:38.588000+00:00", "position": 1}, {"session_key": 9566, "meeting_key": 1241, "driver_number": 81, "date": "2024-07-21T14:10:38.588000+00:00", "position": 2}, {"session_key": 9566, "meeting_key": 1241, "driver_number": 4, "date": "2024-07-21T14:10:45.425000+00:00", "position": 2}, {"session_key": 9566, "meeting_key": 1241, "driver_number": 81, "date": "2024-07-21T14:10:45.425000+00:00", "position": 3}, {"session_key": 9566, "meeting_key": 1241, "driver_number": 44, "date": "2024-07-21T14:10:52.515000+00:00", "position": 4}, {"session_key": 9566, "meeting_key": 1241, "driver_number": 55, "date": "2024-07-21T14:10:52.515000+00:00", "position": 5}, {"session_key": 9566, "meeting_key": 1241, "driver_number": 16, "date": "2024-07-21T14:10:53.963000+00:00", "position": 5}, {"session_key": 9566, "meeting_key": 1241, "driver_number": 55, "date": "2024-07-21T14:10:53.963000+00:00", "position": 6}, {"session_key": 9566, "meeting_key": 1241, "driver_number": 18, "date": "2024-07-21T14:11:47.027000+00:00", "position": 12}, {"session_key": 9566, "meeting_key": 1241, "driver_number": 27, "date": "2024-07-21T14:11:47.027000+00:00", "position": 13}, {"session_key": 9566, "meeting_key": 1241, "driver_number": 1, "date": "2024-07-21T14:13:29.208000+00:00", "position": 2}, {"session_key": 9566, "meeting_key": 1241, "driver_number": 4, "date": "2024-07-21T14:13:29.208000+00:00", "position": 1}, {"session_key": 9566, "meeting_key": 1241, "driver_number": 1, "date": "2024-07-21T14:13:33.044000+00:00", "position": 3}, {"session_key": 9566, "meeting_key": 1241, "driver_number": 81, "date": "2024-07-21T14:13:33.044000+00:00", "position": 2}, {"session_key": 9566, "meeting_key": 1241, "driver_number": 1, "date": "2024-07-21T14:13:38.018000+00:00", "position": 4}, {"session_key": 9566, "meeting_key": 1241, "driver_number": 44, "date": "2024-07-21T14:13:38.018000+00:00", "position": 3}, {"session_key": 9566, "meeting_key": 1241, "driver_number": 1, "date": "2024-07-21T14:13:39.454000+00:00", "position": 5}, {"session_key": 9566, "meeting_key": 1241, "driver_number": 16, "date": "2024-07-21T14:13:39.454000+00:00", "position": 4}, {"session_key": 9566, "meeting_key": 1241, "driver_number": 11, "date": "2024-07-21T14:19:36.636000+00:00", "position": 7}, {"session_key": 9566, "meeting_key": 1241, "driver_number": 63, "date": "2024-07-21T14:19:36.636000+00:00", "position": 8}, {"session_key": 9566, "meeting_key": 1241, "driver_number": 3, "date": "2024-07-21T14:21:26.569000+00:00", "position": 12}, {"session_key": 9566, "meeting_key": 1241, "driver_number": 18, "date": "2024-07-21T14:21:26.569000+00:00", "position": 11}, {"session_key": 9566, "meeting_key": 1241, "driver_number": 1, "date": "2024-07-21T14:23:19.189000+00:00", "position": 4}, {"session_key": 9566, "meeting_key": 1241, "driver_number": 16, "date": "2024-07-21T14:23:19.189000+00:00", "position": 5}, {"session_key": 9566, "meeting_key": 1241, "driver_number": 2, "date": "2024-07-21T14:30:27.414000+00:00", "position": 18}, {"session_key": 9566, "meeting_key": 1241, "driver_number": 77, "date": "2024-07-21T14:30:27.414000+00:00", "position": 17}, {"session_key": 9566, "meeting_key": 1241, "driver_number": 1, "date": "2024-07-21T14:31:38.557000+00:00", "position": 5}, {"session_key": 9566, "meeting_key": 1241, "driver_number": 16, "date": "2024-07-21T14:31:38.557000+00:00", "position": 4}, {"session_key": 9566, "meeting_key": 1241, "driver_number": 31, "date": "2024-07-21T14:34:42.038000+00:00", "position": 17}, {"session_key": 9566, "meeting_key": 1241, "driver_number": 77, "date": "2024-07-21T14:34:42.038000+00:00", "position": 16}, {"session_key": 9566, "meeting_key": 1241, "driver_number": 2, "date": "2024-07-21T14:34:57.943000+00:00", "position": 19}, {"session_key": 9566, "meeting_key": 1241, "driver_number": 24, "date": "2024-07-21T14:34:57.943000+00:00", "position": 18}, {"session_key": 9566, "meeting_key": 1241, "driver_number": 14, "date": "2024-07-21T14:35:19.127000+00:00", "position": 11}, {"session_key": 9566, "meeting_key": 1241, "driver_number": 18, "date": "2024-07-21T14:35:19.127000+00:00", "position": 10}, {"session_key": 9566, "meeting_key": 1241, "driver_number": 24, "date": "2024-07-21T14:36:22.702000+00:00", "position": 17}, {"session_key": 9566, "meeting_key": 1241, "driver_number": 31, "date": "2024-07-21T14:36:22.702000+00:00", "position": 18}, {"session_key": 9566, "meeting_key": 1241, "driver_number": 2, "date": "2024-07-21T14:36:25.309000+00:00", "position": 18}, {"session_key": 9566, "meeting_key": 1241, "driver_number": 31, "date": "2024-07-21T14:36:25.309000+00:00", "position": 19}, {"session_key": 9566, "meeting_key": 1241, "driver_number": 4, "date": "2024-07-21T14:38:15.296000+00:00", "position": 2}, {"session_key": 9566, "meeting_key": 1241, "driver_number": 81, "date": "2024-07-21T14:38:15.296000+00:00", "position": 1}, {"session_key": 9566, "meeting_key": 1241, "driver_number": 2, "date": "2024-07-21T14:39:09.828000+00:00", "position": 17}, {"session_key": 9566, "meeting_key": 1241, "driver_number": 24, "date": "2024-07-21T14:39:09.828000+00:00", "position": 18}, {"session_key": 9566, "meeting_key": 1241, "driver_number": 24, "date": "2024-07-21T14:42:01.899000+00:00", "position": 19}, {"session_key": 9566, "meeting_key": 1241, "driver_number": 31, "date": "2024-07-21T14:42:01.899000+00:00", "position": 18}]